EggplantLibrary/__init__.py
EggplantLibrary/libcore.py
EggplantLibrary/utils.py
EggplantLibrary/version.py
robotframework_eggplantlibrary-22.1.8.dist-info/LICENSE
robotframework_eggplantlibrary-22.1.8.dist-info/METADATA
robotframework_eggplantlibrary-22.1.8.dist-info/WHEEL
robotframework_eggplantlibrary-22.1.8.dist-info/top_level.txt
robotframework_eggplantlibrary-22.1.8.dist-info/RECORD
