Metadata-Version: 2.1
Name: robotframework-eggplantlibrary
Version: 22.1.8
Summary: Robot Framework eggPlant Library
Home-page: https://github.com/amochin/robotframework-eggplant
Author: Andrei Mochinin
License: Apache License 2.0
Classifier: Programming Language :: Python :: 3
Classifier: Operating System :: Microsoft :: Windows
Classifier: License :: OSI Approved :: Apache Software License
Classifier: Framework :: Robot Framework :: Library
Requires-Python: >=3.9
License-File: LICENSE
Requires-Dist: robotframework
Requires-Dist: Pillow
